{
  "": "",
  "А": "А",
  "Авторизация": "Авторизация",
  "Возраст": "Возраст",
  "Войти": "Войти",
  "Вход": "Вход",
  "Вы ввели неверный логин или пароль": "Вы ввели неверный логин или пароль",
  "Выйти": "Выйти",
  "Главная": "Главная",
  "Город": "Город",
  "Зарегистрироваться": "Зарегистрироваться",
  "Изменить": "Изменить",
  "Имя": "Имя",
  "Не удалось запросить информацию о пользователе": "Не удалось запросить информацию о пользователе",
  "Не удалось запросить список тудушек": "Не удалось запросить список тудушек",
  "Не удалось зарегистрироваться": "Не удалось зарегистрироваться",
  "Не удалось обновить информацию о пользователе": "Не удалось обновить информацию о пользователе",
  "Ник": "Ник",
  "О нас": "О нас",
  "Отмена": "Отмена",
  "Ошибка при выходе из профиля": "Ошибка при выходе из профиля",
  "Ошибка при загрузке": "Ошибка при загрузке",
  "П": "П",
  "Пароль": "Пароль",
  "Перевести": "Перевести",
  "Попробуйте обновить страницу": "Попробуйте обновить страницу",
  "Попробуйте перезагрузить страницу": "Попробуйте перезагрузить страницу",
  "Почта": "Почта",
  "Произошла непредвиденная ошибка": "Произошла непредвиденная ошибка",
  "Произошла ошибка": "Произошла ошибка",
  "Профиль": "Профиль",
  "Регистрация": "Регистрация",
  "Редактировать профиль": "Редактировать профиль",
  "С": "С",
  "Светлая тема": "Светлая тема",
  "Сохранить": "Сохранить",
  "Списки задач": "Списки задач",
  "Список дел": "Список дел",
  "Страна": "Страна",
  "Страница не найдена": "Страница не найдена",
  "Темная тема": "Темная тема",
  "Фамилия": "Фамилия",
  "Фото профиля": "Фото профиля",
  "Язык интерфейса": "Язык интерфейса",
  "ру": "ру",
  "рус": "рус"
}
